README.rst
setup.cfg
setup.py
flightrecorder/__init__.py
flightrecorder/base.py
flightrecorder/common.py
flightrecorder/errors.py
flightrecorder/fifty20.py
flightrecorder/firmware.py
flightrecorder/flightrecorder.py
flightrecorder/flymaster.py
flightrecorder/nmea.py
flightrecorder/serialio.py
flightrecorder/sixty15.py
flightrecorder/utc.py
flightrecorder/waypoint.py
flightrecorder.egg-info/PKG-INFO
flightrecorder.egg-info/SOURCES.txt
flightrecorder.egg-info/dependency_links.txt
flightrecorder.egg-info/top_level.txt
flightrecorder.egg-info/zip-safe
scripts/flightrecorder