Metadata-Version: 1.0
Name: flightrecorder
Version: 0.9.3
Summary: Utilities for flight recorders
Home-page: https://github.com/twpayne/flightrecorder
Author: Tom Payne
Author-email: twpayne@gmail.com
License: UNKNOWN
Platform: UNKNOWN
